dg_calculations/__init__.py
dg_calculations/duration.py
dg_calculations/conversions/__init__.py
dg_calculations/conversions/area.py
dg_calculations/conversions/length.py
dg_calculations/conversions/mass.py
dg_calculations/conversions/temperature.py
dg_calculations/conversions/volumes.py
dg_calculations-0.0.5.dist-info/LICENSE
dg_calculations-0.0.5.dist-info/METADATA
dg_calculations-0.0.5.dist-info/WHEEL
dg_calculations-0.0.5.dist-info/top_level.txt
dg_calculations-0.0.5.dist-info/RECORD
