Metadata-Version: 2.1
Name: dg-calculations
Version: 0.0.5
Summary: A simple package to allow the addition of durations such as CD lengths. (for now)
Home-page: https://github.com/dazed-gerbil/dg_calculations
Author: Calum Andrew Morrell
Author-email: floss@dazed-gerbil.com
License: BSD 3-Clause License
Project-URL: Bug Tracker, https://github.com/dazed-gerbil/dg_calculations/issues
Platform: UNKNOWN
Classifier: Programming Language :: Python :: 3
Classifier: Programming Language :: Python :: 3.6
Classifier: Programming Language :: Python :: 3.7
Classifier: Programming Language :: Python :: 3.8
Classifier: Programming Language :: Python :: 3.9
Classifier: Programming Language :: Python :: 3.10
Classifier: License :: OSI Approved :: BSD License
Classifier: Operating System :: OS Independent
Classifier: Development Status :: 3 - Alpha
Requires-Python: >=3.6
License-File: LICENSE
